LICENSE.txt
README.md
setup.cfg
setup.py
os_tools/logger_handler.py
os_tools/string_utils.py
os_tools/tools.py
os_tools.egg-info/PKG-INFO
os_tools.egg-info/SOURCES.txt
os_tools.egg-info/dependency_links.txt
os_tools.egg-info/top_level.txt