Metadata-Version: 2.1
Name: os-tools
Version: 4.56
Summary: py tools for os
Home-page: https://github.com/osfunapps/os-tools-py
Author: Oz Shabat
Author-email: osfunapps@gmail.com
License: MIT
Keywords: python,osfunapps,files,tools,utils
Platform: UNKNOWN
Classifier: Development Status :: 5 - Production/Stable
Classifier: Intended Audience :: Developers
Classifier: Topic :: Software Development :: Build Tools
Classifier: License :: OSI Approved :: MIT License
Classifier: Programming Language :: Python :: 3
Classifier: Programming Language :: Python :: 3.4
Classifier: Programming Language :: Python :: 3.5
Classifier: Programming Language :: Python :: 3.6
Classifier: Programming Language :: Python :: 3.9
License-File: LICENSE.txt
